<?xml version="1.0" encoding="UTF-8"?><record_update>
    <sys_choice action="DELETE" field="u_application" table="x_271208_panomator_requests" version="3">
        <sys_choice action="INSERT_OR_UPDATE">
            <dependent_value/>
            <element>u_application</element>
            <hint/>
            <inactive>false</inactive>
            <label>any</label>
            <language>en</language>
            <name>x_271208_panomator_requests</name>
            <sequence>0</sequence>
            <sys_created_by>admin</sys_created_by>
            <sys_created_on>2020-06-02 20:55:32</sys_created_on>
            <sys_domain>global</sys_domain>
            <sys_domain_path>/</sys_domain_path>
            <sys_id>1b6cf35bdb01101026cacc3039961976</sys_id>
            <sys_mod_count>0</sys_mod_count>
            <sys_updated_by>admin</sys_updated_by>
            <sys_updated_on>2020-06-02 20:55:32</sys_updated_on>
            <value>any</value>
        </sys_choice>
        <sys_choice action="INSERT_OR_UPDATE">
            <dependent_value/>
            <element>u_application</element>
            <hint/>
            <inactive>false</inactive>
            <label>dns</label>
            <language>en</language>
            <name>x_271208_panomator_requests</name>
            <sequence>1</sequence>
            <sys_created_by>admin</sys_created_by>
            <sys_created_on>2020-06-02 20:55:32</sys_created_on>
            <sys_domain>global</sys_domain>
            <sys_domain_path>/</sys_domain_path>
            <sys_id>5b6cf35bdb01101026cacc3039961976</sys_id>
            <sys_mod_count>0</sys_mod_count>
            <sys_updated_by>admin</sys_updated_by>
            <sys_updated_on>2020-06-02 20:55:32</sys_updated_on>
            <value>dns</value>
        </sys_choice>
        <sys_choice action="INSERT_OR_UPDATE">
            <dependent_value/>
            <element>u_application</element>
            <hint/>
            <inactive>false</inactive>
            <label>ftp</label>
            <language>en</language>
            <name>x_271208_panomator_requests</name>
            <sequence>2</sequence>
            <sys_created_by>admin</sys_created_by>
            <sys_created_on>2020-06-02 20:55:32</sys_created_on>
            <sys_domain>global</sys_domain>
            <sys_domain_path>/</sys_domain_path>
            <sys_id>9b6cf35bdb01101026cacc3039961976</sys_id>
            <sys_mod_count>0</sys_mod_count>
            <sys_updated_by>admin</sys_updated_by>
            <sys_updated_on>2020-06-02 20:55:32</sys_updated_on>
            <value>ftp</value>
        </sys_choice>
        <sys_choice action="INSERT_OR_UPDATE">
            <dependent_value/>
            <element>u_application</element>
            <hint/>
            <inactive>false</inactive>
            <label>ntp</label>
            <language>en</language>
            <name>x_271208_panomator_requests</name>
            <sequence>3</sequence>
            <sys_created_by>admin</sys_created_by>
            <sys_created_on>2020-06-02 20:55:32</sys_created_on>
            <sys_domain>global</sys_domain>
            <sys_domain_path>/</sys_domain_path>
            <sys_id>db6cf35bdb01101026cacc3039961976</sys_id>
            <sys_mod_count>0</sys_mod_count>
            <sys_updated_by>admin</sys_updated_by>
            <sys_updated_on>2020-06-02 20:55:32</sys_updated_on>
            <value>ntp</value>
        </sys_choice>
        <sys_choice action="INSERT_OR_UPDATE">
            <dependent_value/>
            <element>u_application</element>
            <hint/>
            <inactive>false</inactive>
            <label>snmp</label>
            <language>en</language>
            <name>x_271208_panomator_requests</name>
            <sequence>4</sequence>
            <sys_created_by>admin</sys_created_by>
            <sys_created_on>2020-06-02 20:55:32</sys_created_on>
            <sys_domain>global</sys_domain>
            <sys_domain_path>/</sys_domain_path>
            <sys_id>1f6cf35bdb01101026cacc3039961976</sys_id>
            <sys_mod_count>0</sys_mod_count>
            <sys_updated_by>admin</sys_updated_by>
            <sys_updated_on>2020-06-02 20:55:32</sys_updated_on>
            <value>snmp</value>
        </sys_choice>
        <sys_choice action="INSERT_OR_UPDATE">
            <dependent_value/>
            <element>u_application</element>
            <hint/>
            <inactive>false</inactive>
            <label>ssh</label>
            <language>en</language>
            <name>x_271208_panomator_requests</name>
            <sequence>5</sequence>
            <sys_created_by>admin</sys_created_by>
            <sys_created_on>2020-06-02 20:55:32</sys_created_on>
            <sys_domain>global</sys_domain>
            <sys_domain_path>/</sys_domain_path>
            <sys_id>5f6cf35bdb01101026cacc3039961976</sys_id>
            <sys_mod_count>0</sys_mod_count>
            <sys_updated_by>admin</sys_updated_by>
            <sys_updated_on>2020-06-02 20:55:32</sys_updated_on>
            <value>ssh</value>
        </sys_choice>
        <sys_choice action="INSERT_OR_UPDATE">
            <dependent_value/>
            <element>u_application</element>
            <hint/>
            <inactive>false</inactive>
            <label>ssl</label>
            <language>en</language>
            <name>x_271208_panomator_requests</name>
            <sequence>6</sequence>
            <sys_created_by>admin</sys_created_by>
            <sys_created_on>2020-06-02 20:55:32</sys_created_on>
            <sys_domain>global</sys_domain>
            <sys_domain_path>/</sys_domain_path>
            <sys_id>9f6cf35bdb01101026cacc3039961976</sys_id>
            <sys_mod_count>0</sys_mod_count>
            <sys_updated_by>admin</sys_updated_by>
            <sys_updated_on>2020-06-02 20:55:32</sys_updated_on>
            <value>ssl</value>
        </sys_choice>
        <sys_choice_set action="INSERT_OR_UPDATE">
            <element>u_application</element>
            <name>x_271208_panomator_requests</name>
            <sys_class_name>sys_choice_set</sys_class_name>
            <sys_created_by>admin</sys_created_by>
            <sys_created_on>2020-06-02 20:55:32</sys_created_on>
            <sys_id>936cf35bdb01101026cacc3039961977</sys_id>
            <sys_mod_count>0</sys_mod_count>
            <sys_name>u_application</sys_name>
            <sys_package display_value="Panomator" source="x_271208_panomator">6f358c63db3123005357da75ca961905</sys_package>
            <sys_policy/>
            <sys_scope display_value="Panomator">6f358c63db3123005357da75ca961905</sys_scope>
            <sys_update_name>sys_choice_x_271208_panomator_requests_u_application</sys_update_name>
            <sys_updated_by>admin</sys_updated_by>
            <sys_updated_on>2020-06-02 20:55:32</sys_updated_on>
        </sys_choice_set>
    </sys_choice>
    <sys_update_version action="INSERT_OR_UPDATE">
        <action>DELETE</action>
        <application display_value="Panomator">6f358c63db3123005357da75ca961905</application>
        <file_path/>
        <instance_id>870ce02fdbf8fb409df22f17d496193f</instance_id>
        <instance_name>dev82146</instance_name>
        <name>sys_choice_x_271208_panomator_requests_u_application</name>
        <payload><![CDATA[<?xml version="1.0" encoding="UTF-8"?><record_update><sys_choice action="INSERT_OR_UPDATE" field="u_application" table="x_271208_panomator_requests" version="3"><sys_choice action="INSERT_OR_UPDATE"><dependent_value/><element>u_application</element><hint/><inactive>false</inactive><label>any</label><language>en</language><name>x_271208_panomator_requests</name><sequence>0</sequence><sys_created_by>admin</sys_created_by><sys_created_on>2020-06-02 20:55:32</sys_created_on><sys_domain>global</sys_domain><sys_domain_path>/</sys_domain_path><sys_id>1b6cf35bdb01101026cacc3039961976</sys_id><sys_mod_count>0</sys_mod_count><sys_updated_by>admin</sys_updated_by><sys_updated_on>2020-06-02 20:55:32</sys_updated_on><value>any</value></sys_choice><sys_choice action="INSERT_OR_UPDATE"><dependent_value/><element>u_application</element><hint/><inactive>false</inactive><label>dns</label><language>en</language><name>x_271208_panomator_requests</name><sequence>1</sequence><sys_created_by>admin</sys_created_by><sys_created_on>2020-06-02 20:55:32</sys_created_on><sys_domain>global</sys_domain><sys_domain_path>/</sys_domain_path><sys_id>5b6cf35bdb01101026cacc3039961976</sys_id><sys_mod_count>0</sys_mod_count><sys_updated_by>admin</sys_updated_by><sys_updated_on>2020-06-02 20:55:32</sys_updated_on><value>dns</value></sys_choice><sys_choice action="INSERT_OR_UPDATE"><dependent_value/><element>u_application</element><hint/><inactive>false</inactive><label>ftp</label><language>en</language><name>x_271208_panomator_requests</name><sequence>2</sequence><sys_created_by>admin</sys_created_by><sys_created_on>2020-06-02 20:55:32</sys_created_on><sys_domain>global</sys_domain><sys_domain_path>/</sys_domain_path><sys_id>9b6cf35bdb01101026cacc3039961976</sys_id><sys_mod_count>0</sys_mod_count><sys_updated_by>admin</sys_updated_by><sys_updated_on>2020-06-02 20:55:32</sys_updated_on><value>ftp</value></sys_choice><sys_choice action="INSERT_OR_UPDATE"><dependent_value/><element>u_application</element><hint/><inactive>false</inactive><label>ntp</label><language>en</language><name>x_271208_panomator_requests</name><sequence>3</sequence><sys_created_by>admin</sys_created_by><sys_created_on>2020-06-02 20:55:32</sys_created_on><sys_domain>global</sys_domain><sys_domain_path>/</sys_domain_path><sys_id>db6cf35bdb01101026cacc3039961976</sys_id><sys_mod_count>0</sys_mod_count><sys_updated_by>admin</sys_updated_by><sys_updated_on>2020-06-02 20:55:32</sys_updated_on><value>ntp</value></sys_choice><sys_choice action="INSERT_OR_UPDATE"><dependent_value/><element>u_application</element><hint/><inactive>false</inactive><label>snmp</label><language>en</language><name>x_271208_panomator_requests</name><sequence>4</sequence><sys_created_by>admin</sys_created_by><sys_created_on>2020-06-02 20:55:32</sys_created_on><sys_domain>global</sys_domain><sys_domain_path>/</sys_domain_path><sys_id>1f6cf35bdb01101026cacc3039961976</sys_id><sys_mod_count>0</sys_mod_count><sys_updated_by>admin</sys_updated_by><sys_updated_on>2020-06-02 20:55:32</sys_updated_on><value>snmp</value></sys_choice><sys_choice action="INSERT_OR_UPDATE"><dependent_value/><element>u_application</element><hint/><inactive>false</inactive><label>ssh</label><language>en</language><name>x_271208_panomator_requests</name><sequence>5</sequence><sys_created_by>admin</sys_created_by><sys_created_on>2020-06-02 20:55:32</sys_created_on><sys_domain>global</sys_domain><sys_domain_path>/</sys_domain_path><sys_id>5f6cf35bdb01101026cacc3039961976</sys_id><sys_mod_count>0</sys_mod_count><sys_updated_by>admin</sys_updated_by><sys_updated_on>2020-06-02 20:55:32</sys_updated_on><value>ssh</value></sys_choice><sys_choice action="INSERT_OR_UPDATE"><dependent_value/><element>u_application</element><hint/><inactive>false</inactive><label>ssl</label><language>en</language><name>x_271208_panomator_requests</name><sequence>6</sequence><sys_created_by>admin</sys_created_by><sys_created_on>2020-06-02 20:55:32</sys_created_on><sys_domain>global</sys_domain><sys_domain_path>/</sys_domain_path><sys_id>9f6cf35bdb01101026cacc3039961976</sys_id><sys_mod_count>0</sys_mod_count><sys_updated_by>admin</sys_updated_by><sys_updated_on>2020-06-02 20:55:32</sys_updated_on><value>ssl</value></sys_choice><sys_choice_set action="INSERT_OR_UPDATE"><element>u_application</element><name>x_271208_panomator_requests</name><sys_class_name>sys_choice_set</sys_class_name><sys_created_by>admin</sys_created_by><sys_created_on>2020-06-02 20:55:32</sys_created_on><sys_id>936cf35bdb01101026cacc3039961977</sys_id><sys_mod_count>0</sys_mod_count><sys_name>u_application</sys_name><sys_package display_value="Panomator" source="x_271208_panomator">6f358c63db3123005357da75ca961905</sys_package><sys_policy/><sys_scope display_value="Panomator">6f358c63db3123005357da75ca961905</sys_scope><sys_update_name>sys_choice_x_271208_panomator_requests_u_application</sys_update_name><sys_updated_by>admin</sys_updated_by><sys_updated_on>2020-06-02 20:55:32</sys_updated_on></sys_choice_set></sys_choice></record_update>]]></payload>
        <payload_hash>-413619185</payload_hash>
        <record_name>Request.Application</record_name>
        <reverted_from/>
        <source>a6d5cb52db01101026cacc303996196a</source>
        <source_table>sys_upgrade_history</source_table>
        <state>previous</state>
        <sys_created_by/>
        <sys_created_on>2020-05-30 14:23:09</sys_created_on>
        <sys_id>4d7c775bdb01101026cacc3039961978</sys_id>
        <sys_mod_count/>
        <sys_recorded_at>17265f70cc80000000</sys_recorded_at>
        <sys_updated_by/>
        <sys_updated_on/>
        <type>Choice list</type>
        <update_guid>0d7c775be0011010c199af0128371678</update_guid>
        <update_guid_history>0d7c775be0011010c199af0128371678:-413619185</update_guid_history>
    </sys_update_version>
    <sys_metadata_delete action="INSERT_OR_UPDATE">
        <sys_audit_delete/>
        <sys_class_name>sys_metadata_delete</sys_class_name>
        <sys_created_by>admin</sys_created_by>
        <sys_created_on>2020-06-02 20:55:39</sys_created_on>
        <sys_db_object display_value="" name="sys_choice_set">sys_choice_set</sys_db_object>
        <sys_id>936cf35bdb01101026cacc3039961977</sys_id>
        <sys_metadata>936cf35bdb01101026cacc3039961977</sys_metadata>
        <sys_mod_count>0</sys_mod_count>
        <sys_name>u_application</sys_name>
        <sys_package display_value="Panomator" source="x_271208_panomator">6f358c63db3123005357da75ca961905</sys_package>
        <sys_parent/>
        <sys_policy/>
        <sys_scope display_value="Panomator">6f358c63db3123005357da75ca961905</sys_scope>
        <sys_scope_delete display_value="">5050a7006dd046de9270313ba18023a9</sys_scope_delete>
        <sys_update_name>sys_choice_x_271208_panomator_requests_u_application</sys_update_name>
        <sys_update_version display_value="sys_choice_x_271208_panomator_requests_u_application">4d7c775bdb01101026cacc3039961978</sys_update_version>
        <sys_updated_by>admin</sys_updated_by>
        <sys_updated_on>2020-06-02 20:55:39</sys_updated_on>
    </sys_metadata_delete>
</record_update>
